pydelica/__init__.py
pydelica/compiler.py
pydelica/exception.py
pydelica/logger.py
pydelica/model.py
pydelica/solutions.py
pydelica/options/__init__.py
pydelica/options/library.py
pydelica/options/runtime.py
pydelica/options/simulation.py
pydelica-0.6.3.dist-info/METADATA
pydelica-0.6.3.dist-info/WHEEL
pydelica-0.6.3.dist-info/licenses/LICENSE
pydelica-0.6.3.dist-info/RECORD
