Metadata-Version: 2.4
Name: pydelica
Version: 0.6.3
Summary: Light-weight serverless API for OpenModelica
Project-URL: repository, https://gitlab.com/krizar/pydelica
Author-email: Kristian Zarebski <krizar312@gmail.com>
License: MIT License
License-File: LICENSE
Classifier: Development Status :: 5 - Production/Stable
Classifier: Intended Audience :: Science/Research
Classifier: License :: OSI Approved :: MIT License
Classifier: Natural Language :: English
Classifier: Operating System :: Microsoft :: Windows
Classifier: Operating System :: Unix
Classifier: Programming Language :: Python :: 3
Classifier: Programming Language :: Python :: 3.10
Classifier: Programming Language :: Python :: 3.11
Classifier: Programming Language :: Python :: 3.12
Classifier: Programming Language :: Python :: 3.13
Classifier: Programming Language :: Python :: 3.14
Classifier: Topic :: Scientific/Engineering
Requires-Python: <3.15,>=3.10
Requires-Dist: defusedxml>=0.7.1
Requires-Dist: pandas>=2.2.3
Requires-Dist: pydantic>=2.11.4
